Testing
WikiDataPy
