Metadata-Version: 2.1
Name: WikiDataPy
Version: 0.0.2
Summary: WikidataPy is a Python library designed for seamless interaction with Wikidata's knowledgebase, enabling users to perform a variety of operations such as searching entities, retrieving claims, performing SPARQL queries, and even visualizing knowledge graphs.
Author: Aryan Sethi
License: MIT
License-File: LICENSE.txt
Requires-Dist: requests>=2.32.3
Requires-Dist: pandas>=1.0.0
Requires-Dist: networkx>=2.5
Requires-Dist: matplotlib>=3.9.2
Requires-Dist: networkx>=3.4.2
Requires-Dist: numpy>=2.1.3
Requires-Dist: tabulate>=0.9.0
Requires-Dist: matplotlib-inline>=0.1.7
